nttt/__init__.py
nttt/_version.py
nttt/acknowledgements.py
nttt/arguments.py
nttt/cleanup_formatting.py
nttt/cleanup_html.py
nttt/cleanup_markdown.py
nttt/cleanup_sections.py
nttt/constants.py
nttt/nttt_logging.py
nttt/tidyup.py
nttt/utilities.py
nttt-0.5.3.dist-info/METADATA
nttt-0.5.3.dist-info/WHEEL
nttt-0.5.3.dist-info/entry_points.txt
nttt-0.5.3.dist-info/top_level.txt
nttt-0.5.3.dist-info/RECORD
