Metadata-Version: 2.1
Name: nttt
Version: 0.5.3
Summary: A utility for Nina to clean up translated projects
Home-page: https://github.com/raspberrypilearning/nttt
Author: Raspberry Pi Foundation
Author-email: web@raspberrypi.org
License: UNKNOWN
Keywords: nttt,pypi,package
Platform: UNKNOWN
Requires-Python: >=3.7
Requires-Dist: pandas
Requires-Dist: eol
Requires-Dist: ruamel.yaml
